python_picnic_api/__init__.py
python_picnic_api/client.py
python_picnic_api/helper.py
python_picnic_api/session.py
python_picnic_api-1.1.0.dist-info/LICENSE.md
python_picnic_api-1.1.0.dist-info/WHEEL
python_picnic_api-1.1.0.dist-info/METADATA
python_picnic_api-1.1.0.dist-info/RECORD
